wordcounter_cli/__init__.py
wordcounter_cli/cli.py
crgwordcounter-0.1.0.dist-info/METADATA
crgwordcounter-0.1.0.dist-info/WHEEL
crgwordcounter-0.1.0.dist-info/entry_points.txt
crgwordcounter-0.1.0.dist-info/top_level.txt
crgwordcounter-0.1.0.dist-info/RECORD
