Metadata-Version: 2.4
Name: crgwordcounter
Version: 0.1.0
Summary: Command Line tool to process a text file and output the word frequency of its content.
Home-page: https://git.epam.com/claudio_rodriguez1/test-automation/-/tree/main/test-automation/tips-and-tricks?ref_type=heads
Author: CORG
Author-email: rgz.claudio@gmail.com
Classifier: Programming Language :: Python :: 3
Classifier: License :: OSI Approved :: MIT License
Requires-Python: >=3.6
Dynamic: author
Dynamic: author-email
Dynamic: classifier
Dynamic: description
Dynamic: description-content-type
Dynamic: home-page
Dynamic: requires-python
Dynamic: summary
